Modulos/Azure.py
Modulos/Cloud.py
Modulos/Docker.py
Modulos/GCP.py
Modulos/__init__.py
godoystonecli-0.2.data/scripts/stone_cli
godoystonecli-0.2.dist-info/METADATA
godoystonecli-0.2.dist-info/WHEEL
godoystonecli-0.2.dist-info/top_level.txt
godoystonecli-0.2.dist-info/RECORD
