Metadata-Version: 2.1
Name: godoystonecli
Version: 0.2
Summary: Cria tudo automático
Home-page: https://github.com/blabla
Author: Fernando Godoy
Author-email: fgodoy@stone.com.br
License: UNKNOWN
Platform: UNKNOWN
Classifier: Programming Language :: Python :: 3
Classifier: License :: OSI Approved :: MIT License
Classifier: Operating System :: OS Independent
